iqtrade/__init__.py
iqtrade/api.py
iqtrade-0.0.5.dist-info/LICENSE
iqtrade-0.0.5.dist-info/METADATA
iqtrade-0.0.5.dist-info/WHEEL
iqtrade-0.0.5.dist-info/top_level.txt
iqtrade-0.0.5.dist-info/RECORD
