Metadata-Version: 2.1
Name: iqtrade
Version: 0.0.5
Summary: Python wrapper around Questrade IQ API
Home-page: https://github.com/jpflouret/iqtrade
Author: JP Flouret
Author-email: jpflouret@gmail.com
Requires-Python: >=3.9
License-File: LICENSE
Requires-Dist: requests
